metadata_driver_filecoin/__init__.py
metadata_driver_filecoin/data_plugin.py
nevermined_metadata_driver_filecoin-0.3.0.dist-info/LICENSE
nevermined_metadata_driver_filecoin-0.3.0.dist-info/METADATA
nevermined_metadata_driver_filecoin-0.3.0.dist-info/NOTICE
nevermined_metadata_driver_filecoin-0.3.0.dist-info/WHEEL
nevermined_metadata_driver_filecoin-0.3.0.dist-info/top_level.txt
nevermined_metadata_driver_filecoin-0.3.0.dist-info/RECORD
