Metadata-Version: 2.1
Name: nevermined-metadata-driver-filecoin
Version: 0.3.0
Summary: 💧 Metadata Filecoin Data Driver Implementation
Home-page: https://github.com/nevermined-io/metadata-driver-filecoin
Author: nevermined-io
Author-email: root@nevermined.io
License: Apache Software License 2.0
Keywords: nevermined-metadata-driver-filecoin
Platform: UNKNOWN
Classifier: Development Status :: 5 - Production/Stable
Classifier: Intended Audience :: Developers
Classifier: License :: OSI Approved :: Apache Software License
Classifier: Natural Language :: English
Classifier: Programming Language :: Python :: 3.7
Classifier: Programming Language :: Python :: 3.8
License-File: LICENSE
License-File: NOTICE
Requires-Dist: coloredlogs
Requires-Dist: requests (>=2.26.0)
Requires-Dist: requests-toolbelt (>=0.9.1)
Requires-Dist: nevermined-metadata-driver-interface (==0.1.5)
Provides-Extra: dev
Requires-Dist: bumpversion ; extra == 'dev'
Requires-Dist: pkginfo ; extra == 'dev'
Requires-Dist: twine ; extra == 'dev'
Requires-Dist: watchdog ; extra == 'dev'
Requires-Dist: codacy-coverage ; extra == 'dev'
Requires-Dist: coverage ; extra == 'dev'
Requires-Dist: pylint ; extra == 'dev'
Requires-Dist: pytest ; extra == 'dev'
Requires-Dist: pytest-watch ; extra == 'dev'
Provides-Extra: test
Requires-Dist: codacy-coverage ; extra == 'test'
Requires-Dist: coverage ; extra == 'test'
Requires-Dist: pylint ; extra == 'test'
Requires-Dist: pytest ; extra == 'test'
Requires-Dist: pytest-watch ; extra == 'test'
